Workbook

Sheet 0_Lectura
A1: CASO 09 — MULTITIENDAS ANCOA S.A. · Licitación TFEP-01/2026
A2: Catálogo de requerimientos — versión 3.1 (conciliado con el alcance del Subdocumento 3)
A3: Estado | B3: Borrador por revisar (2026-10-08). Es la fuente del Anexo B del Subdocumento 3 («OnlySimpleSolutions-Subdocumento3-Anexos»). No reemplaza al archivo RequerimientosAtomizados_Depuracion_Alcance.xlsx (v3.0), que se conserva sin cambios; si ambos difieren, decide el equipo.
A5: MÉTODO
A6: Fuentes | B6: Levantamiento documental, sin entrevistas a interesados: Caso 09, Bases Administrativas y Bases Técnicas Transversales. Del Caso salen un registro de 60 reglas de negocio (hoja 5) y las 25 decisiones del numeral 16.1.
A7: Atomización (v3.0) | B7: Cada enunciado del catálogo previo (202 RF y 54 RNF) se evaluó contra cinco reglas: conjunción, verbo único, testabilidad aislada, estructura canónica «[actor o el sistema] debe [verbo] [entidad] [condición]» y separación RF/RNF. Criterio de detención: no se divide la enumeración de valores de un mismo campo. 41 enunciados se dividieron o reclasificaron y las obligaciones de la oferta se separaron como OP.
A8: Depuración de alcance | B8: Las 28 propuestas de la hoja 2 se decidieron con el alcance del Subdocumento 3 (exclusiones, supuestos, plan alternativo del crédito y criterios de aceptación).
A9: Clasificación (nueva en v3.1) | B9: Cada requerimiento lleva servicio dueño del dato, etapa, prioridad MoSCoW (alta o media) y ámbito. La etapa es la del servicio. Alta: servicio de la Etapa 1, todo RNF, toda OP y lo que sostiene una restricción no negociable. Media: servicio de la Etapa 2.
A10: Tipos | B10: RF: lo que el sistema hace. RNF: cuán bien lo hace, con umbral o criterio y método de verificación. OP: obligación de la oferta que no se prueba como función del software.
A11: Colores de la hoja 1 | B11: Azul claro: RF. Verde claro: RNF. Naranja claro: OP.
A13: RESULTADO
A14: Catálogo previo (v3.0) | B14: 307 filas: 223 RF, 75 RNF y 9 OP. Las cifras 226, 76 y 311 de la hoja 0_Lectura de la v3.0 estaban desactualizadas.
A15: Tras la depuración | B15: 303 filas: se elimina RF-027 y se reclasifican RNF-61, RNF-62 y RNF-63 como criterios de aceptación.
A16: Vigente en v3.1 | B16: 308 filas: 227 RF, 72 RNF y 9 OP. Incluye cinco RF nuevos para el servicio de clientes Retail (RF-227 a RF-231).
A18: CAMBIOS RESPECTO DE LA v3.0
A19: Eliminado | B19: RF-027 (presupone etiquetas electrónicas, excluidas por EXC-02).
A20: Reclasificados | B20: RNF-61, RNF-62 y RNF-63 pasan a criterios de aceptación del capítulo 18 (subsección 3.2.5).
A21: Agregados | B21: RF-227 a RF-231, propuestos para el servicio de clientes Retail, que no tenía requerimientos. Por validar con el cliente al inicio del proyecto.
A22: Autonomía sin enlace | B22: RNF-24, RNF-25, RNF-26 y RNF-28 quedan en 24 horas (Bases Técnicas Transversales RT-03.10 y art. 16.4 de las Bases Administrativas).
A23: Reasignaciones | B23: Ver hoja 3: 18 requerimientos cambian de servicio, etapa o prioridad. 10 RNF pasan a la Etapa 2 por el servicio que miden.
A24: Reglas propuestas | B24: Las cinco reglas citadas como «propuesta» (RN-07, RN-42, RN-43, RN-44, RN-45) se renombran RN-P01 a RN-P05 porque colisionaban con reglas definidas.
A25: Pendientes | B25: Ver hoja 8.

Sheet 1_Catalogo_Vigente
A1: ID | B1: Tipo | C1: Requerimiento | D1: Código | E1: Servicio | F1: Frente | G1: Etapa | H1: Prioridad | I1: Ámbito | J1: Umbral o criterio | K1: Método de verificación | L1: RN vinculada | M1: Nota | N1: ID de origen | O1: ID anterior (v3.0)
A2: RF-001 | B2: RF | C2: El sistema deberá permitir la venta física de la unidad aunque exista una reserva temporal activa en el canal digital. | D2: R:V-02 | E2: Servicio de ventas | F2: Retail | G2: 1 | H2: Alta | I2: Retail | J2: — | K2: — | L2: RN-10 | N2: — | O2: RF-010.6
A3: RF-002 | B3: RF | C3: El sistema deberá exigir credenciales individuales al usuario antes de habilitar cualquier acción. | D3: — | E3: Base tecnológica | F3: Ambos | G3: 1 | H3: Alta | I3: Ambos | J3: — | K3: — | L3: RN-50, RN-52 | N3: — | O3: RF-044.1
A4: RF-003 | B4: RF | C4: El sistema debe impedir el acceso anónimo a una terminal. | D4: — | E4: Base tecnológica | F4: Ambos | G4: 1 | H4: Alta | I4: Ambos | J4: — | K4: — | L4: RN-50, RN-52 | N4: RF-044.2 | O4: RF-044.2a
A5: RF-004 | B5: RF | C5: El sistema debe impedir el acceso mediante credencial compartida. | D5: — | E5: Base tecnológica | F5: Ambos | G5: 1 | H5: Alta | I5: Ambos | J5: — | K5: — | L5: RN-50, RN-52 | N5: RF-044.2 | O5: RF-044.2b
A6: RF-005 | B6: RF | C6: El sistema deberá permitir el traspaso de sesión nominativa entre usuarios en una terminal compartida. | D6: — | E6: Base tecnológica | F6: Ambos | G6: 1 | H6: Alta | I6: Ambos | J6: — | K6: — | L6: RN-50 | N6: — | O6: RF-044.3
A7: RF-006 | B7: RF | C7: El sistema deberá cerrar automáticamente la sesión por inactividad en la terminal compartida. | D7: — | E7: Base tecnológica | F7: Ambos | G7: 1 | H7: Alta | I7: Ambos | J7: — | K7: — | L7: RN-50 | N7: — | O7: RF-044.4
A8: RF-007 | B8: RF | C8: El sistema deberá impedir la ejecución de la función de originación a un usuario sin capacitación normativa acreditada y vigente. | D8: — | E8: Base tecnológica | F8: Ambos | G8: 1 | H8: Alta | I8: Ambos | J8: — | K8: — | L8: RN-53 | N8: — | O8: RF-101
A9: RF-008 | B9: RF | C9: El sistema deberá impedir la ejecución de la función de repactación a un usuario sin capacitación normativa acreditada y vigente. | D9: — | E9: Base tecnológica | F9: Ambos | G9: 1 | H9: Alta | I9: Ambos | J9: — | K9: — | L9: RN-53 | N9: — | O9: RF-102
A10: RF-009 | B10: RF | C10: El sistema deberá revocar automáticamente la habilitación funcional del usuario al vencer su acreditación de capacitación. | D10: — | E10: Base tecnológica | F10: Ambos | G10: 1 | H10: Alta | I10: Ambos | J10: — | K10: — | L10: RN-53, RN-52 | N10: — | O10: RF-103
A11: RF-010 | B11: RF | C11: El sistema deberá permitir al proveedor patrocinar la habilitación temporal de acceso de su repositor externo, con fecha de término declarada. | D11: — | E11: Base tecnológica | F11: Ambos | G11: 1 | H11: Alta | I11: Ambos | J11: — | K11: — | L11: RN-51 | N11: — | O11: RF-115
A12: RF-011 | B12: RF | C12: El sistema deberá caducar automáticamente la habilitación de acceso del personal externo al cumplirse su vigencia. | D12: — | E12: Base tecnológica | F12: Ambos | G12: 1 | H12: Alta | I12: Ambos | J12: — | K12: — | L12: RN-51 | N12: — | O12: RF-116
A13: RF-012 | B13: RF | C13: El sistema deberá registrar de forma individualizada el acceso y la actividad del personal externo. | D13: — | E13: Base tecnológica | F13: Ambos | G13: 1 | H13: Alta | I13: Ambos | J13: — | K13: — | L13: RN-51 | N13: — | O13: RF-117
... A36: RF-034 | B36: RF | C36: El sistema deberá evaluar la aplicabilidad de la promoción según la tienda en que se realiza la venta. | D36: R:M-01 | E36: Servicio de oferta comercial | F36: Retail | G36: 1 | H36: Alta | I36: Retail | J36: — | K36: — | L36: RN-20 | N36: — | O36: RF-070
A37: RF-035 | B37: RF | C37: El sistema deberá crear una reserva temporal para la unidad agregada al carro. | D37: R:M-03 | E37: Servicio de existencias | F37: Retail | G37: 1 | H37: Alta | I37: Retail | J37: — | K37: — | L37: RN-10 | M37: La reserva es dato del servicio de existencias. | N37: — | O37: RF-010.1
A38: RF-036 | B38: RF | C38: El sistema deberá permitir parametrizar el período de vigencia de la reserva temporal. | D38: R:M-03 | E38: Servicio de existencias | F38: Retail | G38: 1 | H38: Alta | I38: Retail | J38: — | K38: — | L38: RN-10 | M38: La reserva es dato del servicio de existencias. | N38: — | O38: RF-010.2
A39: RF-037 | B39: RF | C39: El sistema deberá mantener activa la reserva mientras el cliente mantenga actividad, conforme al período parametrizado. | D39: R:M-03 | E39: Servicio de existencias | F39: Retail | G39: 1 | H39: Alta | I39: Retail | J39: — | K39: — | L39: RN-10 | M39: La reserva es dato del servicio de existencias. | N39: — | O39: RF-010.3
A40: RF-038 | B40: RF | C40: El sistema deberá impedir que una misma unidad sea comprometida simultáneamente en más de una operación de venta digital. | D40: R:M-03 | E40: Servicio de existencias | F40: Retail | G40: 1 | H40: Alta | I40: Retail | J40: — | K40: — | L40: RN-10, RN-08 | M40: Impedir el doble compromiso de una unidad es parte de la reserva, dato del servicio de existencias. | N40: — | O40: RF-010.4
A41: RF-039 | B41: RF | C41: El sistema debe liberar la reserva temporal al expirar su período de vigencia. | D41: R:M-03 | E41: Servicio de existencias | F41: Retail | G41: 1 | H41: Alta | I41: Retail | J41: — | K41: — | L41: RN-10 | M41: La reserva es dato del servicio de existencias. | N41: RF-010.5 | O41: RF-010.5a
A42: RF-040 | B42: RF | C42: El sistema debe devolver la unidad liberada al disponible para vender. | D42: R:M-03 | E42: Servicio de existencias | F42: Retail | G42: 1 | H42: Alta | I42: Retail | J42: — | K42: — | L42: RN-10 | M42: La reserva es dato del servicio de existencias. | N42: RF-010.5 | O42: RF-010.5b
A43: RF-041 | B43: RF | C43: El sistema deberá liberar de inmediato la reserva digital de esa unidad, sin esperar la expiración del período. | D43: R:M-03 | E43: Servicio de existencias | F43: Retail | G43: 1 | H43: Alta | I43: Retail | J43: — | K43: — | L43: RN-10 | M43: La reserva es dato del servicio de existencias. | N43: — | O43: RF-010.7
A44: RF-042 | B44: RF | C44: El sistema deberá aplicar el período de vigencia de reserva reducido declarado como parámetro para el evento anual. | D44: R:M-03 | E44: Servicio de existencias | F44: Retail | G44: 1 | H44: Alta | I44: Retail | J44: — | K44: — | L44: RN-10, RN-57 | M44: La reserva es dato del servicio de existencias. | N44: — | O44: RF-010.8
A45: RF-043 | B45: RF | C45: El sistema deberá preautorizar el medio de pago al aceptar el pedido, sin capturar el cobro. | D45: R:V-01 | E45: Servicio de pedidos | F45: Retail | G45: 2 | H45: Media | I45: Retail | J45: — | K45: — | L45: RN-21 | N45: — | O45: RF-011.1
A46: RF-044 | B46: RF | C46: El sistema deberá verificar la existencia física real de la unidad en el punto asignado antes de habilitar la captura del cobro. | D46: R:M-03 | E46: Servicio de existencias | F46: Retail | G46: 1 | H46: Alta | I46: Retail | J46: — | K46: — | L46: RN-21 | M46: La reserva es dato del servicio de existencias. | N46: — | O46: RF-011.2
A47: RF-045 | B47: RF | C47: El sistema deberá capturar el cobro únicamente al registrarse el evento de confirmación de la preparacion física. | D47: R:V-01 | E47: Servicio de pedidos | F47: Retail | G47: 2 | H47: Media | I47: Retail | J47: — | K47: — | L47: RN-21 | N47: — | O47: RF-011.3
A48: RF-046 | B48: RF | C48: El sistema deberá determinar automáticamente la alternativa de resolución aplicable según el motor de reglas (cancelar, sustituir, derivar a tercero o entrega diferida). | D48: R:V-01 | E48: Servicio de pedidos | F48: Retail | G48: 2 | H48: Media | I48: Retail | J48: — | K48: — | L48: RN-23 | N48: — | O48: RF-011.4
A49: RF-047 | B49: RF | C49: El sistema deberá requerir la aceptación explícita del cliente antes de capturar el cobro. | D49: R:V-01 | E49: Servicio de pedidos | F49: Retail | G49: 2 | H49: Media | I49: Retail | J49: — | K49: — | L49: RN-23, RN-21 | N49: — | O49: RF-011.5
A50: RF-048 | B50: RF | C50: El sistema deberá anular la preautorización de pago del pedido. | D50: R:V-01 | E50: Servicio de pedidos | F50: Retail | G50: 2 | H50: Media | I50: Retail | J50: — | K50: — | L50: RN-21, RN-23 | N50: — | O50: RF-011.6
A51: RF-049 | B51: RF | C51: El sistema deberá cancelar el pedido registrando el motivo de la cancelación. | D51: R:V-01 | E51: Servicio de pedidos | F51: Retail | G51: 2 | H51: Media | I51: Retail | J51: — | K51: — | L51: RN-23 | N51: — | O51: RF-011.7
A52: RF-050 | B52: RF | C52: El sistema deberá generar la conciliación diaria de preautorizaciones vencidas sin captura. | D52: R:V-01 | E52: Servicio de pedidos | F52: Retail | G52: 2 | H52: Media | I52: Retail | J52: — | K52: — | L52: RN-21 | N52: — | O52: RF-011.8
A53: RF-051 | B53: RF | C53: El sistema deberá notificar al cliente el cambio de estado de su pedido antes de efectuar cualquier cobro definitivo. | D53: R:V-01 | E53: Servicio de pedidos | F53: Retail | G53: 2 | H53: Media | I53: Retail | J53: — | K53: — | L53: RN-23 | N53: — | O53: RF-011.9
A54: RF-052 | B54: RF | C54: El sistema deberá permitir a todos los actores consultar el estado del pedido desde una única fuente de verdad. | D54: R:V-01 | E54: Servicio de pedidos | F54: Retail | G54: 2 | H54: Media | I54: Retail | J54: — | K54: — | L54: RN-23, RN-28 | N54: — | O54: RF-012
A55: RF-053 | B55: RF | C55: El sistema deberá permitir marcar como no elegible para cumplimiento digital el stock de exhibición de las categorías declaradas. | D55: R:V-01 | E55: Servicio de pedidos | F55: Retail | G55: 2 | H55: Media | I55: Retail | J55: — | K55: — | L55: RN-22, RN-08 | N55: — | O55: RF-013
A56: RF-054 | B56: RF | C56: El sistema debe calcular la base de comisión reconociendo al vendedor y a la tienda de origen de la unidad. | D56: R:V-03 | E56: Servicio de comisiones | F56: Retail | G56: 2 | H56: Media | I56: Retail | J56: — | K56: — | L56: RN-54 | N56: RF-014 | O56: RF-014a
A57: RF-055 | B57: RF | C57: El sistema debe condicionar la transmisión de la base de comisión al movimiento real de inventario verificado en bodega. | D57: R:V-03 | E57: Servicio de comisiones | F57: Retail | G57: 2 | H57: Media | I57: Retail | J57: — | K57: — | L57: RN-54 | N57: RF-014 | O57: RF-014b
A58: RF-056 | B58: RF | C58: El sistema deberá reasignar el pedido a otro punto de despacho con existencia disponible. | D58: R:V-01 | E58: Servicio de pedidos | F58: Retail | G58: 2 | H58: Media | I58: Retail | J58: — | K58: — | L58: RN-23 | M58: Reasignar el pedido es parte del ciclo del pedido. | N58: — | O58: RF-015.1
A59: RF-057 | B59: RF | C59: El sistema deberá impedir una segunda reasignación del mismo pedido. | D59: R:V-01 | E59: Servicio de pedidos | F59: Retail | G59: 2 | H59: Media | I59: Retail | J59: — | K59: — | L59: RN-23 | N59: — | O59: RF-015.2
A60: RF-058 | B60: RF | C60: El sistema deberá acotar la reasignación a la ventana de tiempo parametrizada. | D60: R:V-01 | E60: Servicio de pedidos | F60: Retail | G60: 2 | H60: Media | I60: Retail | J60: — | K60: — | L60: RN-23 | N60: — | O60: RF-015.3
A61: RF-059 | B61: RF | C61: El sistema deberá ofrecer al cliente un producto equivalente. | D61: R:V-01 | E61: Servicio de pedidos | F61: Retail | G61: 2 | H61: Media | I61: Retail | J61: — | K61: — | L61: RN-23 | N61: — | O61: RF-015.4
A62: RF-060 | B62: RF | C62: El sistema deberá ofrecer al cliente la espera compensada con la compensación parametrizada. | D62: R:V-01 | E62: Servicio de pedidos | F62: Retail | G62: 2 | H62: Media | I62: Retail | J62: — | K62: — | L62: RN-23 | N62: — | O62: RF-015.5
A63: RF-061 | B63: RF | C63: El sistema deberá ofrecer al cliente la liberacion del pedido con anulación de la preautorización. | D63: R:V-01 | E63: Servicio de pedidos | F63: Retail | G63: 2 | H63: Media | I63: Retail | J63: — | K63: — | L63: RN-23, RN-21 | N63: — | O63: RF-015.6
A64: RF-062 | B64: RF | C64: El sistema debe monitorear el tiempo restante de cada pedido respecto de su fecha prometida de entrega. | D64: R:V-01 | E64: Servicio de pedidos | F64: Retail | G64: 2 | H64: Media | I64: Retail | J64: — | K64: — | L64: RN-24 | N64: RF-035 | O64: RF-035a
A65: RF-063 | B65: RF | C65: El sistema debe priorizar la preparación del pedido al alcanzar el umbral parametrizado de tiempo restante. | D65: R:V-01 | E65: Servicio de pedidos | F65: Retail | G65: 2 | H65: Media | I65: Retail | J65: — | K65: — | L65: RN-24 | N65: RF-035 | O65: RF-035b
A66: RF-064 | B66: RF | C66: El sistema debe permitir al cliente no autenticado consultar el precio vigente de una referencia. | D66: R:M-01 | E66: Servicio de oferta comercial | F66: Retail | G66: 1 | H66: Alta | I66: Retail | J66: — | K66: — | L66: RN-17, RN-11 | M66: El precio vigente es dato del servicio de oferta comercial. La consulta pública es parte del portal de la Etapa 1. | N66: RF-036A | O66: RF-036A.1
A67: RF-065 | B67: RF | C67: El sistema debe permitir al cliente no autenticado consultar la disponibilidad de la referencia por tienda. | D67: R:M-03 | E67: Servicio de existencias | F67: Retail | G67: 1 | H67: Alta | I67: Retail | J67: — | K67: — | L67: RN-17, RN-11 | M67: La disponibilidad es dato del servicio de existencias. La consulta pública es parte del portal de la Etapa 1. | N67: RF-036A | O67: RF-036A.2
A68: RF-066 | B68: RF | C68: El sistema debe permitir al cliente no autenticado consultar la disponibilidad de la referencia para despacho. | D68: R:M-03 | E68: Servicio de existencias | F68: Retail | G68: 1 | H68: Alta | I68: Retail | J68: — | K68: — | L68: RN-17, RN-11 | M68: La disponibilidad es dato del servicio de existencias. La consulta pública es parte del portal de la Etapa 1. | N68: RF-036A | O68: RF-036A.3
A69: RF-067 | B69: RF | C69: El sistema debe permitir al cliente autenticado consultar sus compras. | D69: R:V-01 | E69: Servicio de pedidos | F69: Retail | G69: 2 | H69: Media | I69: Retail | J69: — | K69: — | L69: RN-02, RN-04 | N69: RF-037 | O69: RF-037.1
A70: RF-068 | B70: RF | C70: El sistema debe permitir al cliente autenticado consultar sus devoluciones. | D70: R:V-01 | E70: Servicio de pedidos | F70: Retail | G70: 2 | H70: Media | I70: Retail | J70: — | K70: — | L70: RN-02, RN-04 | N70: RF-037 | O70: RF-037.2
A71: RF-069 | B71: RF | C71: El sistema debe permitir al cliente autenticado consultar su estado de cuenta. | D71: F:C-02 | E71: Servicio de cartera de crédito | F71: Filial emisora | G71: 2 | H71: Media | I71: Filial emisora | J71: — | K71: — | L71: RN-02, RN-04 | M71: El estado de cuenta es dato de la filial emisora y la consulta pasa por el control de cruces (RF-165 y RF-174). Portal del cliente de la Etapa 2. | N71: RF-037 | O71: RF-037.3
A72: RF-070 | B72: RF | C72: El sistema debe permitir al cliente autenticado consultar sus documentos. | D72: F:C-02 | E72: Servicio de cartera de crédito | F72: Filial emisora | G72: 2 | H72: Media | I72: Filial emisora | J72: — | K72: — | L72: RN-02, RN-04 | M72: Los documentos del crédito son datos de la filial emisora y la consulta pasa por el control de cruces (RF-165 y RF-174). Portal del cliente de la Etapa 2. | N72: RF-037 | O72: RF-037.4
A73: RF-071 | B73: RF | C73: El sistema deberá calcular la base de comisión considerando el canal de origen y el canal de cumplimiento cuando estos difieran. | D73: R:V-03 | E73: Servicio de comisiones | F73: Retail | G73: 2 | H73: Media | I73: Retail | J73: — | K73: — | L73: RN-54 | M73: Mantenido: EXC-05 exige calcular la base de comisión entre canales y RF-054 no considera el canal de cumplimiento. | N73: — | O73: RF-040
A74: RF-072 | B74: RF | C74: El sistema debe permitir al ejecutivo de mesón consultar el estado real del pedido. | D74: R:V-01 | E74: Servicio de pedidos | F74: Retail | G74: 2 | H74: Media | I74: Retail | J74: — | K74: — | L74: RN-16, RN-23 | N74: RF-049 | O74: RF-049a
A75: RF-073 | B75: RF | C75: El sistema debe permitir al ejecutivo de mesón consultar el precio aplicado al pedido. | D75: R:V-01 | E75: Servicio de pedidos | F75: Retail | G75: 2 | H75: Media | I75: Retail | J75: — | K75: — | L75: RN-16, RN-23 | N75: RF-049 | O75: RF-049b
A76: RF-074 | B76: RF | C76: El sistema debe permitir al ejecutivo de mesón ofrecer al cliente las opciones de resolución definidas en RF-059, RF-060 y RF-061. | D76: R:V-01 | E76: Servicio de pedidos | F76: Retail | G76: 2 | H76: Media | I76: Retail | J76: — | K76: — | L76: RN-16, RN-23 | N76: RF-049 | O76: RF-049c
A77: RF-075 | B77: RF | C77: El sistema deberá excluir al centro de distribución de Concepción como origen de promesa de entrega en el canal digital mientras no este acreditado su sistema de gestión de almacenes. | D77: R:V-01 | E77: Servicio de pedidos | F77: Retail | G77: 2 | H77: Media | I77: Retail | J77: — | K77: — | L77: RN-15 | N77: — | O77: RF-057
A78: RF-076 | B78: RF | C78: El sistema deberá calcular el costo total de servir de cada punto de despacho candidato, incorporando costo logístico, costo de oportunidad de sala y plazo comprometido. | D78: R:V-01 | E78: Servicio de pedidos | F78: Retail | G78: 2 | H78: Media | I78: Retail | J78: — | K78: — | L78: RN-22 | N78: — | O78: RF-071
A79: RF-077 | B79: RF | C79: El sistema deberá seleccionar como punto de despacho aquel de menor costo total de servir. | D79: R:V-01 | E79: Servicio de pedidos | F79: Retail | G79: 2 | H79: Media | I79: Retail | J79: — | K79: — | L79: RN-22 | N79: — | O79: RF-072
A80: RF-078 | B80: RF | C80: El sistema deberá registrar el valor de cada término del costo total de servir que fundamento la seleccion. | D80: R:V-01 | E80: Servicio de pedidos | F80: Retail | G80: 2 | H80: Media | I80: Retail | J80: — | K80: — | L80: RN-22 | N80: — | O80: RF-073
A81: RF-079 | B81: RF | C81: El sistema deberá calcular la fecha prometida de entrega en función del punto de despacho, la capacidad de preparacion y el transportista asignado. | D81: R:V-01 | E81: Servicio de pedidos | F81: Retail | G81: 2 | H81: Media | I81: Retail | J81: — | K81: — | L81: RN-24 | N81: — | O81: RF-074
A82: RF-080 | B82: RF | C82: El sistema deberá impedir la publicación de un plazo fijo de catálogo como fecha prometida de entrega. | D82: R:V-01 | E82: Servicio de pedidos | F82: Retail | G82: 2 | H82: Media | I82: Retail | J82: — | K82: — | L82: RN-24 | N82: — | O82: RF-075
A83: RF-081 | B83: RF | C83: El sistema deberá calcular el cumplimiento de la promesa de entrega por pedido individual. | D83: R:V-01 | E83: Servicio de pedidos | F83: Retail | G83: 2 | H83: Media | I83: Retail | J83: — | K83: — | L83: RN-24 | N83: — | O83: RF-076
A84: RF-082 | B84: RF | C84: El sistema deberá detectar la pérdida del enlace externo y conmutar automáticamente la tienda a modo desconectado. | D84: R:V-02 | E84: Servicio de ventas | F84: Retail | G84: 1 | H84: Alta | I84: Retail | J84: — | K84: — | L84: RN-46 | N84: — | O84: RF-029.1
A85: RF-083 | B85: RF | C85: El sistema deberá permitir al cajero registrar una venta en modo desconectado. | D85: R:V-02 | E85: Servicio de ventas | F85: Retail | G85: 1 | H85: Alta | I85: Retail | J85: — | K85: — | L85: RN-46 | N85: — | O85: RF-029.2
A86: RF-084 | B86: RF | C86: El sistema deberá permitir al cajero cobrar la venta en modo desconectado. | D86: R:V-02 | E86: Servicio de ventas | F86: Retail | G86: 1 | H86: Alta | I86: Retail | J86: — | K86: — | L86: RN-46 | N86: — | O86: RF-029.3
A87: RF-085 | B87: RF | C87: El sistema deberá aplicar las promociones vigentes en modo desconectado, evaluadas según RF-032, RF-033 y RF-034. | D87: R:V-02 | E87: Servicio de ventas | F87: Retail | G87: 1 | H87: Alta | I87: Retail | J87: — | K87: — | L87: RN-46, RN-20 | M87: El punto de venta aplica la promoción con datos del servicio de oferta comercial. | N87: — | O87: RF-029.4
A88: RF-086 | B88: RF | C88: El sistema deberá emitir el documento de venta en contingencia utilizando folios previamente asignados por el sistema de gestión empresarial. | D88: R:V-02 | E88: Servicio de ventas | F88: Retail | G88: 1 | H88: Alta | I88: Retail | J88: — | K88: — | L88: RN-46, RN-49 | N88: — | O88: RF-029.5
A89: RF-087 | B89: RF | C89: El sistema deberá permitir al vendedor consultar la existencia local de la tienda en modo desconectado. | D89: R:M-03 | E89: Servicio de existencias | F89: Retail | G89: 1 | H89: Alta | I89: Retail | J89: — | K89: — | L89: RN-46 | N89: — | O89: RF-029.6
A90: RF-088 | B90: RF | C90: El sistema deberá detectar el restablecimiento del enlace y conmutar la tienda a modo conectado. | D90: R:V-02 | E90: Servicio de ventas | F90: Retail | G90: 1 | H90: Alta | I90: Retail | J90: — | K90: — | L90: RN-48 | N90: — | O90: RF-029.7
A91: RF-089 | B91: RF | C91: El sistema deberá permitir el otorgamiento de crédito en modo desconectado exclusivamente contra cupo preaprobado vigente almacenado en caché local. | D91: F:C-01 | E91: Servicio de originación de crédito | F91: Filial emisora | G91: 1 | H91: Alta | I91: Filial emisora | J91: — | K91: — | L91: RN-47 | M91: Condicionado al crédito sin conexión (EXC-16, plan alternativo de la subsección 3.2.3). Si la prueba falla, la función se declara no disponible (RT-03.13). | N91: — | O91: RF-104
A92: RF-090 | B92: RF | C92: El sistema deberá aplicar el tope de monto parametrizado a cada operación de crédito cursada en modo desconectado. | D92: F:C-01 | E92: Servicio de originación de crédito | F92: Filial emisora | G92: 1 | H92: Alta | I92: Filial emisora | J92: — | K92: — | L92: RN-47 | M92: Condicionado al crédito sin conexión (EXC-16, plan alternativo de la subsección 3.2.3). Si la prueba falla, la función se declara no disponible (RT-03.13). | N92: — | O92: RF-105
A93: RF-091 | B93: RF | C93: El sistema deberá aplicar el tope parametrizado de número de operaciones de crédito en modo desconectado. | D93: F:C-01 | E93: Servicio de originación de crédito | F93: Filial emisora | G93: 1 | H93: Alta | I93: Filial emisora | J93: — | K93: — | L93: RN-47 | M93: Condicionado al crédito sin conexión (EXC-16, plan alternativo de la subsección 3.2.3). Si la prueba falla, la función se declara no disponible (RT-03.13). | N93: — | O93: RF-106
A94: RF-092 | B94: RF | C94: El sistema deberá impedir la apertura de una tarjeta nueva en modo desconectado. | D94: F:C-01 | E94: Servicio de originación de crédito | F94: Filial emisora | G94: 1 | H94: Alta | I94: Filial emisora | J94: — | K94: — | L94: RN-47 | M94: Aplica EXC-16: no hay apertura ni ampliación de cupo sin conexión. | N94: — | O94: RF-107
A95: RF-093 | B95: RF | C95: El sistema deberá impedir la ampliación de cupo en modo desconectado. | D95: F:C-01 | E95: Servicio de originación de crédito | F95: Filial emisora | G95: 1 | H95: Alta | I95: Filial emisora | J95: — | K95: — | L95: RN-47 | M95: Aplica EXC-16: no hay apertura ni ampliación de cupo sin conexión. | N95: — | O95: RF-108
A96: RF-094 | B96: RF | C96: El sistema deberá marcar la operación como cursada en modo desconectado para su validación posterior. | D96: R:V-02 | E96: Servicio de ventas | F96: Retail | G96: 1 | H96: Alta | I96: Retail | J96: — | K96: — | L96: RN-47, RN-48 | M96: Condicionado al crédito sin conexión (EXC-16, plan alternativo de la subsección 3.2.3). Si la prueba falla, la función se declara no disponible (RT-03.13). | N96: — | O96: RF-109
A97: RF-095 | B97: RF | C97: El sistema debe reconciliar hacia los sistemas centrales la totalidad de las ventas registradas en modo desconectado. | D97: R:V-02 | E97: Servicio de ventas | F97: Retail | G97: 1 | H97: Alta | I97: Retail | J97: — | K97: — | L97: RN-48 | N97: RF-110 | O97: RF-110a
A98: RF-096 | B98: RF | C98: El sistema debe reconciliar hacia los sistemas centrales la totalidad de los documentos emitidos en modo desconectado. | D98: R:V-02 | E98: Servicio de ventas | F98: Retail | G98: 1 | H98: Alta | I98: Retail | J98: — | K98: — | L98: RN-48 | N98: RF-110 | O98: RF-110b
A99: RF-097 | B99: RF | C99: El sistema deberá procesar la reconciliación de forma idempotente, impidiendo la duplicación de ventas o documentos ante reintentos. | D99: R:V-02 | E99: Servicio de ventas | F99: Retail | G99: 1 | H99: Alta | I99: Retail | J99: — | K99: — | L99: RN-48 | N99: — | O99: RF-111
A100: RF-098 | B100: RF | C100: El sistema deberá resolver el conflicto de existencia comprometida aplicando la regla de precedencia declarada, produciendo el mismo resultado ante repetición. | D100: R:M-03 | E100: Servicio de existencias | F100: Retail | G100: 1 | H100: Alta | I100: Retail | J100: — | K100: — | L100: RN-48, RN-08 | N100: — | O100: RF-112
A101: RF-099 | B101: RF | C101: El sistema deberá generar un informe de excepciones de la reconciliación, identificando cada conflicto resuelto y su regla aplicada. | D101: R:V-02 | E101: Servicio de ventas | F101: Retail | G101: 1 | H101: Alta | I101: Retail | J101: — | K101: — | L101: RN-48 | N101: — | O101: RF-113
A102: RF-100 | B102: RF | C102: El sistema deberá enrutar la emisión de todo documento tributario hacia el sistema de gestión empresarial como único emisor. | D102: R:V-02 | E102: Servicio de ventas | F102: Retail | G102: 1 | H102: Alta | I102: Retail | J102: — | K102: — | L102: RN-49 | N102: — | O102: RF-114
A103: RF-101 | B103: RF | C103: El sistema deberá permitir al vendedor de piso consultar la disponibilidad para vender de una referencia. | D103: R:M-03 | E103: Servicio de existencias | F103: Retail | G103: 1 | H103: Alta | I103: Retail | J103: — | K103: — | L103: RN-09, RN-P05 | M103: La disponibilidad para vender es dato del servicio de existencias; la consulta sin conexión usa su copia local. | N103: — | O103: RF-039
A104: OP-06 | B104: OP | C104: El PROPONENTE debe especificar la cantidad de dispositivos móviles requeridos por tienda y por departamento. | D104: — | E104: Gestión del proyecto | F104: — | G104: Todo el proyecto | H104: Alta | I104: — | J104: — | K104: — | L104: RN-60 | N104: RF-120 | O104: OP-06
A105: OP-07 | B105: OP | C105: El PROPONENTE debe especificar las características técnicas de los dispositivos móviles requeridos. | D105: — | E105: Gestión del proyecto | F105: — | G105: Todo el proyecto | H105: Alta | I105: — | J105: — | K105: — | L105: RN-60, RN-50 | N105: RF-121 | O105: OP-07
A106: OP-08 | B106: OP | C106: El PROPONENTE debe presentar el análisis de hacer o comprar del centro de distribución de Concepción con sus tres alternativas. | D106: — | E106: Gestión del proyecto | F106: — | G106: Todo el proyecto | H106: Alta | I106: — | J106: — | K106: — | L106: RN-61, RN-15 | N106: RF-122 | O106: OP-08
A107: OP-09 | B107: OP | C107: El PROPONENTE debe declarar el impacto de la alternativa seleccionada sobre el cumplimiento de RN-15. | D107: — | E107: Gestión del proyecto | F107: — | G107: Todo el proyecto | H107: Alta | I107: — | J107: — | K107: — | L107: RN-61, RN-15 | N107: RF-122 | O107: OP-09
A108: RF-102 | B108: RF | C108: El sistema debe permitir al vendedor de marketplace declarar la existencia de sus referencias. | D108: R:V-04 | E108: Servicio de marketplace | F108: Retail | G108: 2 | H108: Media | I108: Retail | J108: — | K108: — | L108: RN-32 | N108: RF-016A.1 | O108: RF-016A.1a
A109: RF-103 | B109: RF | C109: El sistema debe permitir al vendedor de marketplace actualizar la existencia previamente declarada. | D109: R:V-04 | E109: Servicio de marketplace | F109: Retail | G109: 2 | H109: Media | I109: Retail | J109: — | K109: — | L109: RN-32 | N109: RF-016A.1 | O109: RF-016A.1b
A110: RNF-02 | B110: RNF | C110: La interfaz de declaración de existencia del vendedor de marketplace debe estar disponible de forma continua. | D110: — | E110: Base tecnológica | F110: Ambos | G110: 2 | H110: Alta | I110: Retail | J110: 24x7x365; disponibilidad >= 99,5 % (supuesto fundamentado). | K110: Medición mensual de disponibilidad de la interfaz de sincronización de catálogo. | L110: RN-32 | M110: Mide el servicio de marketplace, de la Etapa 2. | N110: RF-016A.1 | O110: NFR-36
A111: RF-104 | B111: RF | C111: El sistema deberá registrar cada actualización de existencia declarada con su fecha y hora. | D111: R:V-04 | E111: Servicio de marketplace | F111: Retail | G111: 2 | H111: Media | I111: Retail | J111: — | K111: — | L111: RN-32 | N111: — | O111: RF-016A.2
A112: RF-105 | B112: RF | C112: El sistema deberá calcular los indicadores de nivel de servicio por vendedor externo según las reglas publicadas. | D112: R:V-04 | E112: Servicio de marketplace | F112: Retail | G112: 2 | H112: Media | I112: Retail | J112: — | K112: — | L112: RN-30 | N112: — | O112: RF-016B
A113: RF-106 | B113: RF | C113: El sistema deberá notificar al vendedor de marketplace la recepción de la devolución en el momento en que se registra. | D113: R:V-04 | E113: Servicio de marketplace | F113: Retail | G113: 2 | H113: Media | I113: Retail | J113: — | K113: — | L113: RN-28 | N113: — | O113: RF-017.1
A114: RF-107 | B114: RF | C114: El sistema deberá permitir al ejecutivo registrar que parte asume el costo de la devolución. | D114: R:V-04 | E114: Servicio de marketplace | F114: Retail | G114: 2 | H114: Media | I114: Retail | J114: — | K114: — | L114: RN-28, RN-33 | N114: — | O114: RF-017.2
A115: RF-108 | B115: RF | C115: El sistema deberá permitir al ejecutivo registrar la prestación entregada al cliente (reparación, reposición o devolución del precio). | D115: R:V-04 | E115: Servicio de marketplace | F115: Retail | G115: 2 | H115: Media | I115: Retail | J115: — | K115: — | L115: RN-28, RN-29 | N115: — | O115: RF-017.3
A116: RF-109 | B116: RF | C116: El sistema deberá publicar únicamente la existencia declarada en la última actualización vigente del vendedor. | D116: R:V-04 | E116: Servicio de marketplace | F116: Retail | G116: 2 | H116: Media | I116: Retail | J116: — | K116: — | L116: RN-32 | N116: — | O116: RF-018
A117: RF-110 | B117: RF | C117: El sistema debe permitir al vendedor de marketplace consultar el estado de cada pedido intermediado. | D117: R:V-04 | E117: Servicio de marketplace | F117: Retail | G117: 2 | H117: Media | I117: Retail | J117: — | K117: — | L117: RN-30 | N117: RF-038 | O117: RF-038.1
A118: RF-111 | B118: RF | C118: El sistema debe permitir al vendedor de marketplace consultar las devoluciones de sus pedidos. | D118: R:V-04 | E118: Servicio de marketplace | F118: Retail | G118: 2 | H118: Media | I118: Retail | J118: — | K118: — | L118: RN-30 | N118: RF-038 | O118: RF-038.2
A119: RF-112 | B119: RF | C119: El sistema debe permitir al vendedor de marketplace consultar su evaluación de desempeño vigente. | D119: R:V-04 | E119: Servicio de marketplace | F119: Retail | G119: 2 | H119: Media | I119: Retail | J119: — | K119: — | L119: RN-30 | N119: RF-038 | O119: RF-038.3
A120: RF-113 | B120: RF | C120: El sistema debe identificar visiblemente al vendedor de la unidad en el catálogo, la ficha de producto y el proceso de compra. | D120: R:V-04 | E120: Servicio de marketplace | F120: Retail | G120: 2 | H120: Media | I120: Retail | J120: — | K120: — | L120: RN-P03, RN-25 | N120: RF-048.1 | O120: RF-048.1a
A121: RF-114 | B121: RF | C121: El sistema debe identificar visiblemente a quien despacha la unidad en el catálogo, la ficha de producto y el proceso de compra. | D121: R:V-04 | E121: Servicio de marketplace | F121: Retail | G121: 2 | H121: Media | I121: Retail | J121: — | K121: — | L121: RN-P03, RN-25 | N121: RF-048.1 | O121: RF-048.1b
A122: RF-115 | B122: RF | C122: El sistema debe mostrar las condiciones de devolución aplicables a la unidad. | D122: R:V-04 | E122: Servicio de marketplace | F122: Retail | G122: 2 | H122: Media | I122: Retail | J122: — | K122: — | L122: RN-P03, RN-26 | N122: RF-048.2 | O122: RF-048.2a
...

Sheet 2_Depuracion_Alcance
A1: ID | B1: Propuesta | C1: Decisión del equipo | D1: Fundamento
A2: RF-025 | B2: Eliminar | C2: Eliminado (ya fuera del catálogo vigente) | D2: Presupone etiquetas electrónicas, excluidas por EXC-02.
A3: RF-026 | B3: Eliminar | C3: Eliminado (ya fuera del catálogo vigente) | D3: Presupone etiquetas electrónicas, excluidas por EXC-02.
A4: RF-031 | B4: Eliminar | C4: Eliminado (ya fuera del catálogo vigente) | D4: Presupone etiquetas electrónicas, excluidas por EXC-02.
A5: RNF-01 | B5: Eliminar | C5: Eliminado (ya fuera del catálogo vigente) | D5: Presupone etiquetas electrónicas, excluidas por EXC-02.
A6: RF-027 | B6: Eliminar | C6: Eliminado | D6: Presupone etiquetas electrónicas, excluidas por EXC-02 (solo se evalúa, especifica y costea la alternativa).
A7: OP-01 | B7: Trasladar | C7: Mantenida como obligación del proponente | D7: No es función del sistema: es una obligación de la oferta sobre etiquetas electrónicas (EXC-02).
A8: OP-02 | B8: Trasladar | C8: Mantenida como obligación del proponente | D8: No es función del sistema: es una obligación de la oferta sobre etiquetas electrónicas (EXC-02).
A9: OP-03 | B9: Trasladar | C9: Mantenida como obligación del proponente | D9: No es función del sistema: es una obligación de la oferta sobre etiquetas electrónicas (EXC-02).
A10: OP-04 | B10: Trasladar | C10: Mantenida como obligación del proponente | D10: No es función del sistema: es una obligación de la oferta sobre etiquetas electrónicas (EXC-02).
A11: OP-05 | B11: Trasladar | C11: Mantenida como obligación del proponente | D11: No es función del sistema: es una obligación de la oferta sobre etiquetas electrónicas (EXC-02).
A12: OP-06 | B12: Trasladar | C12: Mantenida como obligación del proponente | D12: No es función del sistema: es una obligación de la oferta sobre dispositivos móviles (EXC-03).
... A34: RF-231 | B34: Agregar | C34: Agregado (propuesto por el proponente) | D34: El sistema deberá sincronizar con el sistema de fidelización conservado los datos de fidelización del cliente. Propuesto por el proponente. Deriva de EXC-15: la fidelización se conserva y se integra al servicio. Por validar.

Sheet 3_Reasignaciones
A1: ID | B1: De | C1: A | D1: Etapa | E1: Prioridad | F1: Motivo
A2: RF-038 | B2: Servicio de pedidos | C2: Servicio de existencias | D2: 1 | E2: Alta | F2: Impedir el doble compromiso de una unidad es parte de la reserva, dato del servicio de existencias.
A3: RF-056 | B3: Servicio de existencias | C3: Servicio de pedidos | D3: 2 | E3: Media | F3: Reasignar el pedido es parte del ciclo del pedido.
A4: RF-064 | B4: Servicio de pedidos | C4: Servicio de oferta comercial | D4: 1 | E4: Alta | F4: El precio vigente es dato del servicio de oferta comercial. La consulta pública es parte del portal de la Etapa 1.
A5: RF-065 | B5: Servicio de pedidos | C5: Servicio de existencias | D5: 1 | E5: Alta | F5: La disponibilidad es dato del servicio de existencias. La consulta pública es parte del portal de la Etapa 1.
A6: RF-066 | B6: Servicio de pedidos | C6: Servicio de existencias | D6: 1 | E6: Alta | F6: La disponibilidad es dato del servicio de existencias. La consulta pública es parte del portal de la Etapa 1.
A7: RF-069 | B7: Servicio de pedidos | C7: Servicio de cartera de crédito | D7: 2 | E7: Media | F7: El estado de cuenta es dato de la filial emisora y la consulta pasa por el control de cruces (RF-165 y RF-174). Portal del cliente de la Etapa 2.
A8: RF-070 | B8: Servicio de pedidos | C8: Servicio de cartera de crédito | D8: 2 | E8: Media | F8: Los documentos del crédito son datos de la filial emisora y la consulta pasa por el control de cruces (RF-165 y RF-174). Portal del cliente de la Etapa 2.
A9: RF-101 | B9: Servicio de ventas | C9: Servicio de existencias | D9: 1 | E9: Alta | F9: La disponibilidad para vender es dato del servicio de existencias; la consulta sin conexión usa su copia local.
A10: RF-138 | B10: Servicio de abastecimiento | C10: Servicio de existencias | D10: 1 | E10: Alta | F10: Clasificar la merma de un ajuste de inventario es parte del servicio de existencias, igual que RF-139 a RF-141.
A11: RF-142 | B11: Servicio de existencias | C11: Servicio de oferta comercial | D11: 1 | E11: Alta | F11: Los atributos del maestro de artículos son datos del servicio de oferta comercial.
A12: RF-143 | B12: Servicio de existencias | C12: Servicio de oferta comercial | D12: 1 | E12: Alta | F12: La publicación de la referencia es función del servicio de oferta comercial.
... A31: RNF-69 | B31: Etapa 1 | C31: Etapa 2 | D31: 2 | E31: Alta | F31: Mide el servicio de posventa, de la Etapa 2.

Sheet 4_Resumen
A1: Resumen del catálogo vigente
A2: Los valores se calculan por fórmula sobre la hoja 1_Catalogo_Vigente.
A4: Tipo | B4: Cantidad
A5: Requerimientos funcionales (RF) | B5: =COUNTIF('1_Catalogo_Vigente'!$B$2:$B$309,"RF") -> 227
A6: Requerimientos no funcionales (RNF) | B6: =COUNTIF('1_Catalogo_Vigente'!$B$2:$B$309,"RNF") -> 72
A7: Obligaciones del proponente (OP) | B7: =COUNTIF('1_Catalogo_Vigente'!$B$2:$B$309,"OP") -> 9
A8: Total | B8: =COUNTA('1_Catalogo_Vigente'!$A$2:$A$309) -> 308
A10: Etapa | B10: RF | C10: RNF | D10: OP
A11: Etapa 1 | B11: =COUNTIFS('1_Catalogo_Vigente'!$G$2:$G$309,"1",'1_Catalogo_Vigente'!$B$2:$B$309,"RF") -> 142 | C11: =COUNTIFS('1_Catalogo_Vigente'!$G$2:$G$309,"1",'1_Catalogo_Vigente'!$B$2:$B$309,"RNF") -> 61 | D11: =COUNTIFS('1_Catalogo_Vigente'!$G$2:$G$309,"1",'1_Catalogo_Vigente'!$B$2:$B$309,"OP") -> 0
A12: Etapa 1 y 2 | B12: =COUNTIFS('1_Catalogo_Vigente'!$G$2:$G$309,"1 y 2",'1_Catalogo_Vigente'!$B$2:$B$309,"RF") -> 4 | C12: =COUNTIFS('1_Catalogo_Vigente'!$G$2:$G$309,"1 y 2",'1_Catalogo_Vigente'!$B$2:$B$309,"RNF") -> 0 | D12: =COUNTIFS('1_Catalogo_Vigente'!$G$2:$G$309,"1 y 2",'1_Catalogo_Vigente'!$B$2:$B$309,"OP") -> 0
A13: Etapa 2 | B13: =COUNTIFS('1_Catalogo_Vigente'!$G$2:$G$309,"2",'1_Catalogo_Vigente'!$B$2:$B$309,"RF") -> 81 | C13: =COUNTIFS('1_Catalogo_Vigente'!$G$2:$G$309,"2",'1_Catalogo_Vigente'!$B$2:$B$309,"RNF") -> 11 | D13: =COUNTIFS('1_Catalogo_Vigente'!$G$2:$G$309,"2",'1_Catalogo_Vigente'!$B$2:$B$309,"OP") -> 0
A14: Todo el proyecto | B14: =COUNTIFS('1_Catalogo_Vigente'!$G$2:$G$309,"Todo el proyecto",'1_Catalogo_Vigente'!$B$2:$B$309,"RF") -> 0 | C14: =COUNTIFS('1_Catalogo_Vigente'!$G$2:$G$309,"Todo el proyecto",'1_Catalogo_Vigente'!$B$2:$B$309,"RNF") -> 0 | D14: =COUNTIFS('1_Catalogo_Vigente'!$G$2:$G$309,"Todo el proyecto",'1_Catalogo_Vigente'!$B$2:$B$309,"OP") -> 9
A16: Prioridad | B16: RF | C16: RNF | D16: OP
A17: Alta | B17: =COUNTIFS('1_Catalogo_Vigente'!$H$2:$H$309,"Alta",'1_Catalogo_Vigente'!$B$2:$B$309,"RF") -> 152 | C17: =COUNTIFS('1_Catalogo_Vigente'!$H$2:$H$309,"Alta",'1_Catalogo_Vigente'!$B$2:$B$309,"RNF") -> 72 | D17: =COUNTIFS('1_Catalogo_Vigente'!$H$2:$H$309,"Alta",'1_Catalogo_Vigente'!$B$2:$B$309,"OP") -> 9
A18: Media | B18: =COUNTIFS('1_Catalogo_Vigente'!$H$2:$H$309,"Media",'1_Catalogo_Vigente'!$B$2:$B$309,"RF") -> 75 | C18: =COUNTIFS('1_Catalogo_Vigente'!$H$2:$H$309,"Media",'1_Catalogo_Vigente'!$B$2:$B$309,"RNF") -> 0 | D18: =COUNTIFS('1_Catalogo_Vigente'!$H$2:$H$309,"Media",'1_Catalogo_Vigente'!$B$2:$B$309,"OP") -> 0
A20: Servicio (RF) | B20: RF
A21: Servicio de oferta comercial | B21: =COUNTIFS('1_Catalogo_Vigente'!$E$2:$E$309,"Servicio de oferta comercial",'1_Catalogo_Vigente'!$B$2:$B$309,"RF") -> 20
A22: Servicio de abastecimiento | B22: =COUNTIFS('1_Catalogo_Vigente'!$E$2:$E$309,"Servicio de abastecimiento",'1_Catalogo_Vigente'!$B$2:$B$309,"RF") -> 3
A23: Servicio de existencias | B23: =COUNTIFS('1_Catalogo_Vigente'!$E$2:$E$309,"Servicio de existencias",'1_Catalogo_Vigente'!$B$2:$B$309,"RF") -> 48
A24: Servicio de pedidos | B24: =COUNTIFS('1_Catalogo_Vigente'!$E$2:$E$309,"Servicio de pedidos",'1_Catalogo_Vigente'!$B$2:$B$309,"RF") -> 31
A25: Servicio de ventas | B25: =COUNTIFS('1_Catalogo_Vigente'!$E$2:$E$309,"Servicio de ventas",'1_Catalogo_Vigente'!$B$2:$B$309,"RF") -> 14
A26: Servicio de comisiones | B26: =COUNTIFS('1_Catalogo_Vigente'!$E$2:$E$309,"Servicio de comisiones",'1_Catalogo_Vigente'!$B$2:$B$309,"RF") -> 3
A27: Servicio de marketplace | B27: =COUNTIFS('1_Catalogo_Vigente'!$E$2:$E$309,"Servicio de marketplace",'1_Catalogo_Vigente'!$B$2:$B$309,"RF") -> 25
A28: Servicio de posventa | B28: =COUNTIFS('1_Catalogo_Vigente'!$E$2:$E$309,"Servicio de posventa",'1_Catalogo_Vigente'!$B$2:$B$309,"RF") -> 12
A29: Servicio de clientes Retail | B29: =COUNTIFS('1_Catalogo_Vigente'!$E$2:$E$309,"Servicio de clientes Retail",'1_Catalogo_Vigente'!$B$2:$B$309,"RF") -> 5
A30: Servicio de originación de crédito | B30: =COUNTIFS('1_Catalogo_Vigente'!$E$2:$E$309,"Servicio de originación de crédito",'1_Catalogo_Vigente'!$B$2:$B$309,"RF") -> 14
A31: Servicio de cartera de crédito | B31: =COUNTIFS('1_Catalogo_Vigente'!$E$2:$E$309,"Servicio de cartera de crédito",'1_Catalogo_Vigente'!$B$2:$B$309,"RF") -> 6
A32: Servicio de evidencia financiera | B32: =COUNTIFS('1_Catalogo_Vigente'!$E$2:$E$309,"Servicio de evidencia financiera",'1_Catalogo_Vigente'!$B$2:$B$309,"RF") -> 15
A33: Servicio de control de cruces | B33: =COUNTIFS('1_Catalogo_Vigente'!$E$2:$E$309,"Servicio de control de cruces",'1_Catalogo_Vigente'!$B$2:$B$309,"RF") -> 12
A34: Base tecnológica | B34: =COUNTIFS('1_Catalogo_Vigente'!$E$2:$E$309,"Base tecnológica",'1_Catalogo_Vigente'!$B$2:$B$309,"RF") -> 19
A36: Ámbito (RNF) | B36: RNF
A37: Retail | B37: =COUNTIFS('1_Catalogo_Vigente'!$I$2:$I$309,"Retail",'1_Catalogo_Vigente'!$B$2:$B$309,"RNF") -> 36
A38: Filial emisora | B38: =COUNTIFS('1_Catalogo_Vigente'!$I$2:$I$309,"Filial emisora",'1_Catalogo_Vigente'!$B$2:$B$309,"RNF") -> 16
A39: Ambos | B39: =COUNTIFS('1_Catalogo_Vigente'!$I$2:$I$309,"Ambos",'1_Catalogo_Vigente'!$B$2:$B$309,"RNF") -> 20

Sheet 5_Reglas_Negocio
A1: ID | B1: Regla | C1: Prioridad | D1: Origen | E1: Criterio de aceptación
A2: RN-01 | B2: La compañía debe mantener los datos del retail y los de la filial emisora en dominios separados, lógica y físicamente, en todo momento. | C2: M | D2: Cap. 10, restricción N°1; Cap. 6, fila "Separación del negocio financiero" | E2: Documento de frontera aprobado por la contraloría + prueba de penetración que acredite que un componente del retail no alcanza datos de crédito.
A3: RN-02 | B3: Un dato no puede cruzar entre el ámbito retail y el ámbito fiscalizado si no existe una interfaz declarada, con finalidad, base de licitud, autorización nominada y registro de auditoría. | C3: M | D3: Cap. 16.1, decisión N°4; Cap. 12, Ley 21.719 | E3: Inventario de flujos autorizados; todo intento no declarado queda bloqueado y registrado. Auditoría (ventana por definir con el cliente al inicio del proyecto) sobre 100 % de los cruces.
A4: RN-03 | B4: El área comercial del retail no puede utilizar el comportamiento de pago del cliente (mora, deuda, cupo utilizado) para perfilamiento, segmentación ni campaña. | C4: M | D4: Cap. 12, principio de finalidad, Ley 20.575 | E4: Revisión de los atributos disponibles en el motor de campañas: cero atributos de origen financiero.
A5: RN-04 | B5: La compañía debe identificar a la misma persona con identificadores distintos en cada ámbito, relacionados por una tabla de correspondencia custodiada y no por clave común replicada. | C5: M | D5: Cap. 16.1, decisión N°3 | E5: La clave del ámbito financiero no aparece como columna en ninguna tabla del retail.
A6: RN-05 | B6: Ninguna facilidad comercial puede utilizar datos del ámbito fiscalizado para fines del retail, ni datos del retail para fines crediticios, sin pasar por el control de cruce de RN-02. | C6: M | D6: Cap. 10, restricción N°1; Cap. 6, cierre; Cap. 18, advertencia del directorio | E6: Revisión funcional de toda iniciativa de marketing o CRM: cero variables de origen financiero en el motor de campañas sin registro de cruce autorizado.
A7: RN-06 | B7: El comité de arquitectura no puede aprobar ninguna solución, por su rentabilidad esperada, que reduzca el nivel de separación técnica ya implementado entre los dos ámbitos. | C7: M | D7: Cap. 10, restricción N°1; Cap. 18, advertencia final del directorio (cita textual de la contralora) | E7: Acta de comité con evaluación explícita del impacto en la frontera de datos, previa a la aprobación de cualquier iniciativa comercial.
A8: RN-08 | B8: La compañía no debe comprometer existencia frente al cliente utilizando el registro bruto de inventario. | C8: M | D8: Cap. 4, sección 4.4; Cap. 7, sección 7.1 | E8: Ningún canal consume el saldo bruto: toda publicación pasa por el cálculo de disponible.
A9: RN-09 | B9: El canal de venta debe calcular la existencia disponible para vender restando de la existencia registrada las reservas vigentes, el comprometido no despachado y un colchón de confianza que se adapta según la categoría y el punto de existencia. | C9: M | D9: Cap. 16.1, decisión N°1; Cap. 9, sección 9.1; Cap. 7, sección 7.1 (descuento fijo de 2019) | E9: Fórmula parametrizada y auditable; el colchón toma al menos dos valores distintos entre categorías o entre puntos de existencia; cancelaciones por falta de existencia < 0,3 % anual.(meta del capitulo 7)
A10: RN-10 | B10: El sistema debe reservar la unidad al agregarse al carro, y la reserva debe expirar automáticamente devolviendo la unidad al disponible al cumplirse su vigencia. | C10: M | D10: Cap. 16.1, decisión N°12 | E10: Prueba de expiración con reloj controlado; en evento anual la vigencia se acorta según parámetro declarado.
A11: RN-11 | B11: El canal de venta puede permitir la publicación de una categoría bajo el umbral de exactitud definido, siempre que informe al cliente o al vendedor el porcentaje de error probable, calculado según la categoría y el punto de existencia. | C11: M | D11: Cap. 9, subsección 9.1; Cap. 9, subsección 9.11; Cap. 15, RT-16.21; Cap. 16.1, decisión N°23 | E11: Prueba con categoría bajo umbral: el sistema publica mostrando el % de error calculado, dispara alerta interna, y el rol facultado puede suspender manualmente en ≤ tiempo objetivo. Verificar que no exista bloqueo automático no solicitado.
A12: RN-12 | B12: La compañía debe clasificar la merma en sus componentes y no debe registrarla como un concepto único. | C12: S | D12: Cap. 16.1, decisión N°17; Cap. 9, §9.2; Cap. 18, criterio 27 | E12: Informe mensual de merma con los cinco componentes cuantificados y suma igual al total; hoy el valor es "se desconoce" (Cap. 7, sección 7.1).
... A66: RN-P05 | B66: El vendedor de piso debe poder consultar la disponibilidad para vender junto con su porcentaje de error probable, con respuesta ágil en una terminal compartida. | C66: — | D66: Propuesta del proponente, derivada de RF-101, RF-161, RNF-21. Por validar. | E66: —

Sheet 6_Divisiones_v3.0
A1: ID de origen | B1: Tipo original | C1: Enunciado original (v2.1) | D1: Regla(s) de atomicidad aplicada(s) | E1: IDs resultantes | F1: N° resultantes
A2: RF-044.2 | B2: RF | C2: El sistema deberá impedir el acceso anónimo o con credencial compartida. | D2: Regla 1 (conjunción); Regla 3 (testabilidad aislada) | E2: RF-003, RF-004 | F2: 2
A3: RF-119 | B3: RF | C3: El sistema deberá conciliar los accesos vigentes contra la nómina activa e informar los accesos huérfanos detectados. | D3: Regla 1 (conjunción); Regla 2 (verbo único) | E3: RF-014, RF-015 | F3: 2
A4: RF-034 | B4: RF | C4: El PROPONENTE deberá especificar y costear la alternativa de etiquetas electrónicas frente a las demás opciones, sin asumir su adquisición como parte del alcance. | D4: Regla 2 (verbo único); Regla 5 (separación RF/RNF); hallazgo H-11 | E4: OP-01, OP-02 | F4: 2
A5: RF-042.2 | B5: RF | C5: El sistema deberá generar una alerta operativa al jefe de tienda identificando la etiqueta no confirmada, antes de la apertura de sala. | D5: Regla 5 (separación RF/RNF) | E5: RF-027, RNF-01 | F5: 2
A6: RF-043 | B6: RF | C6: El PROPONENTE deberá especificar la cobertura de despliegue, el hardware requerido y su costo, separadamente del resto de la solución. | D6: Regla 1 (conjunción); hallazgo H-11 | E6: OP-03, OP-04, OP-05 | F6: 3
A7: RF-010.5 | B7: RF | C7: El sistema deberá liberar automáticamente la reserva y devolver la unidad al disponible para vender. | D7: Regla 1 (conjunción); Regla 2 (verbo único) | E7: RF-039, RF-040 | F7: 2
A8: RF-014 | B8: RF | C8: El sistema deberá calcular la base de comisión reconociendo al vendedor y a la tienda de origen, validando previamente contra el movimiento de inventario real. | D8: Regla 1 (conjunción); Regla 2 (verbo único); Regla 3 (testabilidad aislada) | E8: RF-054, RF-055 | F8: 2
A9: RF-035 | B9: RF | C9: El sistema deberá monitorear el tiempo restante de cada pedido respecto de su fecha prometida y priorizar su preparacion al acercarse al límite. | D9: Regla 1 (conjunción); Regla 2 (verbo único) | E9: RF-062, RF-063 | F9: 2
A10: RF-036A | B10: RF | C10: El sistema deberá permitir al cliente no autenticado consultar el precio vigente y la disponibilidad por tienda y para despacho. | D10: Regla 1 (conjunción); Regla 3 (testabilidad aislada) | E10: RF-064, RF-065, RF-066 | F10: 3
A11: RF-037 | B11: RF | C11: El sistema deberá permitir al cliente autenticado consultar sus compras, devoluciones, estado de cuenta y documentos. | D11: Regla 1 (conjunción); Regla 3 (testabilidad aislada) | E11: RF-067, RF-068, RF-069, RF-070 | F11: 4
A12: RF-049 | B12: RF | C12: El sistema deberá permitir al ejecutivo de mesón consultar el estado real del pedido y el precio aplicado, y ofrecer las opciones de resolución definidas en RF-059, RF-060 y RF-061. | D12: Regla 1 (conjunción); Regla 2 (verbo único) | E12: RF-072, RF-073, RF-074 | F12: 3
... A42: NFR-35 | B42: RNF | C42: El tratamiento de datos personales debe cumplir la Ley 21.719, incluyendo finalidad declarada, base de licitud y registro de actividades de tratamiento. | D42: Regla 1 (conjunción); Regla 3 (testabilidad aislada) | E42: RNF-74, RNF-75, RNF-76 | F42: 3
E43: TOTAL | F43: 96

Sheet 7_Hallazgos_v3.0
A1: ID | B1: Tipo | C1: Descripción del hallazgo | D1: Impacto | E1: Tratamiento aplicado | F1: Estrategia de riesgo (PMBOK 6.ª ed., §11.5.2.2)
A2: H-16 | B2: Requerimiento que no es de software | C2: RF-034, RF-043, RF-120, RF-121 y RF-122 exigen al PROPONENTE especificar y costear, no al sistema ejecutar una función. El hallazgo H-11 de la versión anterior lo detectó pero no lo resolvió: las filas siguieron numeradas como RF. | D2: Nueve obligaciones contractuales contaminaban el catálogo funcional y habrían entrado a la EDT como paquetes de desarrollo. | E2: Reclasificadas a OP-01 a OP-09 y separadas del catálogo funcional. Se verifican documentalmente en la Oferta Técnica y en el Entregable 2 de la Oferta Económica. | F2: Evitar
A3: H-17 | B3: Mezcla de funcionalidad y calidad | C3: RF-042.2 incorporaba el plazo «antes de la apertura de sala» y RF-002.5 incorporaba «sin bloquear la operación de venta»; RF-016A.1 incorporaba «en cualquier momento», que es disponibilidad. | D3: Un fallo del umbral habría sido reportado como defecto funcional, y el umbral no tenía método de verificación asignado. | E3: Se extraen RNF-01, RNF-03 y RNF-02 conforme a la Regla 5, cada uno con su métrica y su método de verificación. | F3: Mitigar
A4: H-18 | B4: Consulta compuesta sobre la frontera de datos | C4: RF-037 unía cuatro consultas del cliente autenticado, dos de ellas (estado de cuenta y documentos) sobre datos de la filial emisora fiscalizada. | D4: Mientras el requerimiento fuera uno solo, era imposible aplicarle un control de cruce distinto a la parte financiera. Agrava el hallazgo H-04 de la versión anterior. | E4: Dividido en RF-067 a RF-070. Las consultas del ámbito financiero quedan sujetas a la resolución de identidad de RF-174 y al registro de cruce de RF-165. | F4: Mitigar
A5: H-19 | B5: Requerimientos no confirmados por el equipo | C5: Nueve filas conservan «??» en la columna de revisión: RF-001, RF-018, RF-028, RF-120, RF-170, RF-176, RF-160, RF-181 y RF-183. | D5: Son requerimientos vigentes en el catálogo sin decisión formal de aceptación; dos de ellos (RF-160 y RF-028) tienen impacto directo sobre lo que se publica al consumidor. | E5: Se listan como pendientes de resolución en el período de consultas. Hasta su confirmación se mantienen en el catálogo con la marca de no validados. | F5: Aceptar (activa)
A6: H-20 | B6: Referencia normativa incorrecta | C6: RF-002 cita el requisito RT-11.10 del Capítulo 15 como origen. Ese requisito trata del cifrado a nivel de campo, no del control de acceso. La observación ya estaba anotada en el catálogo v2.1 y no se corrigió. | D6: Una cita de origen incorrecta invalida la verificación de trazabilidad que la Comisión de Expertos aplicará al catálogo. | E6: Se propone sustituir la cita por RT-12.11 (autenticación en el perfil operacional), que es el requisito aplicable a terminales compartidas y credenciales individuales. | F6: Evitar
A7: H-21 | B7: Indicador de negocio catalogado como atributo de calidad | C7: RNF-61, RNF-62 y RNF-63 expresan metas de negocio (tasa de cancelación, cumplimiento de la promesa y exactitud de inventario), no atributos de calidad del software. | D7: Son criterios de aceptación del Capítulo 18 del caso. Catalogados como RNF, el ADJUDICATARIO queda comprometido a un resultado que depende también de la operación del CLIENTE. | E7: Se conservan por su valor contractual, marcados como efectividad de negocio. Se recomienda declarar explícitamente en la Oferta Técnica qué parte del indicador depende de la solución y qué parte de la operación del CLIENTE. | F7: Transferir
A8: H-22 | B8: Dimensión de cálculo no desagregada | C8: RF-058 calculaba el error probable en función de la categoría y del punto de existencia en un solo enunciado, mientras que el colchón de confianza sí estaba desagregado en RF-128 y RF-129. | D8: Inconsistencia de criterio dentro del propio catálogo: dos cálculos equivalentes atomizados con distinto grado de detalle. | E8: Dividido en RF-158 y RF-159 para alinearlo con el criterio ya aplicado al colchón. | F8: Mitigar
A9: Los hallazgos H-01 a H-15 de la versión 2.1 se mantienen vigentes y no se reproducen aquí. Esta hoja recoge únicamente lo detectado en la auditoría de atomicidad.

Sheet 8_Pendientes
A1: N.º | B1: Pendiente
A2: 1 | B2: Abastecimiento (3 RF), comisiones (3) y cartera de crédito (6) tienen pocos requerimientos funcionales. Se completa al llenar el Formulario T-12. Los cinco del servicio de clientes Retail son propuestos.
A3: 2 | B3: Faltan requerimientos para imputación de pagos (RN-42), derecho de retracto (Caso 16.1 n.º 22), gastos de cobranza, disponibilidad publicada en 30 s o menos (RT-05.29), hora de corte de las 07:00, exactitud de inventario diaria y enlace de respaldo en 14 tiendas y Coyhaique (RT-03.24). No se inventaron.
A4: 3 | B4: RNF-05 conserva «POR DEFINIR (propuesta: 30 s)» frente al «tiempo real» del Caso.
A5: 4 | B5: Resolver SUP-08 («cobrar el menor») y SUP-09 (propagación del precio): afecta a RF-023, RF-028 y RNF-19.
A6: 5 | B6: Referencias obsoletas del catálogo previo: RF-160 y RF-161 citan «RF-058» (hoy RF-158 y RF-159), RF-183 cita «RF-026.1» (hoy RF-177 y RF-178), RNF-22 y RNF-23 citan «NFR-06.x» (hoy RNF-16 a RNF-21).
A7: 6 | B7: RN-39 y RN-53 no tienen origen ni criterio de aceptación. RN-07 no existe en el registro original.
A8: 7 | B8: Nueve filas con «??» sin confirmar (hallazgo H-19) y 16 supuestos por umbrales ausentes: se validan con el cliente al inicio del proyecto.
A9: 8 | B9: El capítulo 2 (Tabla 2.6) cuenta RNF-61 a RNF-63 como RNF y dice «≥ 8 h en tienda»; aclarar que la propuesta compromete 24 horas.
A10: 9 | B10: La ubicación de RF-180 y RF-181 (evento anual) se confirma en la arquitectura y en el plan de riesgos.
A11: 10 | B11: Columnas del Caso 17.1 (precondición, resultado esperado, origen en el Caso por requerimiento) y matriz de trazabilidad completa: viven en el Formulario T-12.
A12: 11 | B12: Verificar que ningún requisito de transición (migración de datos, capacitación, marcha blanca) quede huérfano (FEP02 · 18).

Sheet 9_Criterios_Aceptacion
A1: N.º | B1: Resultado esperado | C1: Línea base | D1: Meta | E1: Servicio | F1: Se alcanza | G1: Evidencia | H1: Responsabilidad
A2: 1 | B2: El disponible que se publica incorpora el error conocido del registro y se calcula por categoría y por punto. | C2: Suma de existencias menos un descuento fijo definido en 2019. | D2: Cálculo dinámico por categoría y punto (Caso, cap. 7), con tolerancia respecto del conteo por fijar al inicio del proyecto (propuesta del proponente). | E2: Servicio de existencias | F2: Mes 16, con despliegue gradual por categorías | G2: Prueba del cálculo del disponible con el colchón de confianza por categoría y punto (RF-127 a RF-129). | H2: Proponente, con firma de la Contraparte Técnica
A3: 2 | B3: Los pedidos cancelados por falta de existencia bajan al umbral comprometido, también durante el evento anual. | C3: 1,9 % en el año, 2,7 % en el evento y 2.840 casos en 3 días. | D3: Bajo 0,3 % al año y cero cancelaciones por falta de existencia durante el evento (Caso, cap. 7). Reclasificado desde RNF-61. Mes 16, solo categorías con existencias en producción, medida sin meta de cero. Mes 21, con pedidos, meta completa. | E3: Servicios de existencias y de pedidos | F3: Mes 16 con existencias y primer evento anual posterior al mes 21 con pedidos | G3: Medición mensual de las cancelaciones y medición en cada evento anual. La parte de la solución son las cancelaciones por falta de existencia o por disponible mal calculado. La parte del cliente son las cancelaciones por preparación de pedidos en tienda y centro de distribución. | H3: Compartida entre el proponente y el cliente, con firma de la Contraparte Técnica
A4: 3 | B4: Ningún cliente es cobrado por una unidad que la compañía no puede entregar. | C4: Se cobró y se devolvió ocho días después. | D4: Cero casos (propuesta del proponente). | E4: Servicios de pedidos y de existencias | F4: Mes 21 | G4: Auditoría de los pedidos con cobro capturado sobre un pedido no cumplible (RNF-65). | H4: Proponente, con firma de la Contraparte Técnica
A5: 4 | B5: La exactitud del inventario se mide de forma continua y por categoría, contando sin cerrar la tienda. | C5: Conteo cíclico con 12,4 % de diferencia y sin desglose. | D5: Diferencia de conteo bajo 2 % (Caso, cap. 7). Reclasificado desde RNF-63. | E5: Servicio de existencias | F5: Mes 16 con despliegue gradual por tienda y categoría, y mes 21 en las 22 tiendas | G5: Conteo cíclico por categoría sin cerrar la tienda (RF-131 y RF-135) y exactitud diaria por categoría (RT-05.29). La parte de la solución es el registro y el cálculo de la exactitud. La parte del cliente es la ejecución del conteo en sala según la frecuencia acordada. | H5: Compartida entre el proponente y el cliente, con firma de la Contraparte Técnica
A6: 5 | B6: La merma está separada en sus causas: pérdida física, daño, error de recepción, devolución mal reintegrada y error de digitación. | C6: Merma de 1,9 % de la venta, $ 7.800 millones al año, tratada como un solo problema. | D6: 100 % de los ajustes con causa (propuesta del proponente) y merma bajo 1 % (Caso, cap. 7). | E6: Servicio de existencias | F6: Mes 21 | G6: Informe mensual de merma por causa, cuya suma de componentes es igual al total (RN-12 y RF-138). | H6: Proponente, con firma de la Contraparte Técnica
A7: 6 | B7: Un cambio de precio llega a las cajas, al canal digital y a la sala dentro del plazo comprometido. | C7: Cajas y sitio en minutos y etiqueta hasta 24 horas después. | D7: 5 minutos o menos en cajas y canal digital (RT-09.01). En sala, por definir con la política de precios en sala. | E7: Servicio de oferta comercial | F7: Mes 16 | G7: Medición de la latencia de propagación por destino (RNF-19). | H7: Proponente, con firma de la Contraparte Técnica
A8: 7 | B8: La compañía sabe, en todo momento, cuántos puntos de exhibición están desactualizados y cuáles. | C8: No existe registro de qué etiqueta se cambió ni cuándo. | D8: 100 % de los puntos con estado registrado (propuesta del proponente). | E8: Servicio de oferta comercial | F8: Mes 16 | G8: Indicador diario de puntos de exhibición desactualizados (RF-029). | H8: Proponente, con firma de la Contraparte Técnica
A9: 8 | B9: Se puede acreditar qué precio estaba publicado en cada canal en un instante determinado. | C9: Inexistente. No se puede responder ni a favor ni en contra. | D9: Recuperación en 1 minuto o menos sobre una ventana de tres años (propuesta del proponente, RNF-44 y RNF-58). | E9: Servicio de oferta comercial | F9: Mes 16 | G9: Consulta del precio publicado por fecha, hora y canal (RNF-58). | H9: Proponente, con firma de la Contraparte Técnica
A10: 9 | B10: El precio cobrado es el precio exhibido, verificado por muestreo propio y no por fiscalización externa. | C10: 11 % de discrepancia en la fiscalización de febrero. | D10: 0,5 % o menos, verificado por muestreo propio (propuesta del proponente). La política de precios en sala está pendiente (supuestos SUP-08 y SUP-09). | E10: Servicios de oferta comercial y de ventas | F10: Mes 16 | G10: Muestreo propio de precios cobrados y exhibidos por tienda. La parte de la solución es el precio publicado en cajas y canal digital. La parte del cliente es la etiqueta de sala en la tienda. | H10: Compartida entre el proponente y el cliente, con firma de la Contraparte Técnica
A11: 10 | B11: Un pedido tiene un estado único, consultable por el cliente, la tienda, el mesón, el centro de distribución y el vendedor externo. | C11: Cada canal ve un estado distinto y el mesón no ve los pedidos en línea. | D11: Estado único y consistente en todos los canales (RT-05.29). | E11: Servicio de pedidos | F11: Mes 21 | G11: Auditoría cruzada del estado del pedido entre canales (RF-052 y RNF-04). | H11: Proponente, con firma de la Contraparte Técnica
A12: 11 | B12: La decisión del punto de despacho considera el costo total y el efecto sobre la sala de venta. | C12: Se decide por distancia. | D12: 100 % de las asignaciones con costo total (propuesta del proponente). | E12: Servicio de pedidos | F12: Mes 21 | G12: Registro del costo total en cada asignación de despacho (RF-076 y RF-077). | H12: Proponente, con firma de la Contraparte Técnica
A13: 12 | B13: La tienda que entrega una unidad para un pedido de otro canal recibe el reconocimiento correspondiente. | C13: Inexistente. La unidad a veces no aparece. | D13: 100 % de los despachos desde tienda atribuidos (propuesta del proponente). | E13: Servicio de comisiones | F13: Mes 21 | G13: Registro de la atribución de cada despacho (RF-071, con la base de comisión de RF-054 y RF-055). | H13: Proponente, con firma de la Contraparte Técnica
... A29: 28 | B29: Don Jonathan abre una tarjeta más rápido que hoy y el cliente recibe la información completa, sin que una cosa dependa de la otra. | C29: Tres minutos, y la información se entrega como se puede. | D29: 8 segundos o menos en la evaluación y la información obligatoria antes de aceptar. | E29: Servicios de originación de crédito y de evidencia financiera | F29: Mes 16 | G29: Medición comparada del tiempo de apertura y auditoría de la constancia de entrega. | H29: Proponente, con firma de la Contraparte Técnica
